<?xml version="1.0"?>
<pagescount>
	<html_total>5</html_total>
	<html_done>5</html_done>
	<images>25</images>
	<script>11</script>
	<css/>
	<pdf/>
	<documents/>
	<excel/>
	<powerpoint/>
	<flash/>
	<audios/>
	<videos/>
	<xml/>
	<json/>
	<txt/>
	<autocad/>
	<fonts>154</fonts>
	<scraping_reload>1</scraping_reload>
	<is_pretty_url>false</is_pretty_url>
	<is_ebn>false</is_ebn>
	<email>agundawarr@gmail.com</email>
	<theme_name>WmdTheme486449</theme_name>
	<server_url_front_page>https://www6.waybackmachinedownloader.com/wdo/files/demo/learnforsyth.org_agundawarr_gmail.com_g1glydjf2y/</server_url_front_page>
	<no_www_url>learnforsyth.org</no_www_url>
	<hosted_domain/>
	<original_archive_url>http://learnforsyth.org</original_archive_url>
	<final_archive_url>https://www.learnforsyth.org/</final_archive_url>
	<front_page_code_date/>
	<total_urls_from_api/>
	<max_reached_live>false</max_reached_live>
	<scrape_other_captures>false</scrape_other_captures>
	<total_size>9968</total_size>
	<!-- XML File data for LF site -->
</pagescount>
